{
  "last_updated": "2026-07-13 09:55:44",
  "article_count": 20,
  "articles": [
    {
      "title": "Најдобриот дефанзивец во Евролигата потпиша за Денвер",
      "summary": "Најдобриот дефанзивец на Евролигата, Алфа Дијало, ќе ја продолжи кариерата во НБА, откако се согласи на едногодишен договор вреден 1,4 милиони долари ...",
      "link": "https://makfax.com.mk/sport/najdobriot-defanzivec-vo-evroligata-potpisha-za-denver/",
      "published": "Mon, 13 Jul 2026 07:53:59 +0000",
      "source_name": "МАКФАКС",
      "region": "🏔️ Балкан",
      "category": "Новости",
      "fetched_at": "2026-07-13 09:55:44",
      "language": "unknown"
    },
    {
      "title": "Започна исплатата на субвенциите за велосипеди, повикот за дополнителна опрема е сè уште активен, вели Герасимовски",
      "summary": "Општина Центар почна со исплата на субвенциите за купен велосипед преку проектот „Цел Центар на точак“. На сметките на граѓаните веќе се исплатени прв...",
      "link": "https://makfax.com.mk/makedonija/zapochna-isplatata-na-subvenciite-za-velosipedi-povikot-za-dopolnitelna-oprema-e-se-ushte-aktiven-veli-gerasimovski/",
      "published": "Mon, 13 Jul 2026 07:50:11 +0000",
      "source_name": "МАКФАКС",
      "region": "🏔️ Балкан",
      "category": "Новости",
      "fetched_at": "2026-07-13 09:55:44",
      "language": "unknown"
    },
    {
      "title": "Легендарниот напаѓач стана селектор на Уругвај",
      "summary": "Именуван е наследникот на Марсело Биелса на клупата на уругвајската репрезентација. Тоа ќе биде легендарниот напаѓач на „Ла Селесте“ Диего Форлан. Пре...",
      "link": "https://makfax.com.mk/sport/legendarniot-napagach-stana-selektor-na-urugvaj/",
      "published": "Mon, 13 Jul 2026 07:49:35 +0000",
      "source_name": "МАКФАКС",
      "region": "🏔️ Балкан",
      "category": "Новости",
      "fetched_at": "2026-07-13 09:55:44",
      "language": "unknown"
    },
    {
      "title": "ВЛЕН: „Охридско лето“ е симбол на културата, традицијата и обединувањето на народите",
      "summary": "„Културата е еден од најважните столбови на идентитетот и дијалогот меѓу народите, а настаните како „Охридско лето“ сведочат дека уметноста има моќ да...",
      "link": "https://makfax.com.mk/kultura/vlen-ohridsko-leto-e-simbol-na-kulturata-tradicijata-i-obedinuvanjeto-na-narodite/",
      "published": "Mon, 13 Jul 2026 07:48:21 +0000",
      "source_name": "МАКФАКС",
      "region": "🏔️ Балкан",
      "category": "Новости",
      "fetched_at": "2026-07-13 09:55:44",
      "language": "unknown"
    },
    {
      "title": "(Видео) Унгарскиот премиер на џет-ски во Турција: „Годишен одмор, сè платив сам“",
      "summary": "Унгарскиот премиер Петер Маѓар престојуваше во Анталија со своите синови по самитот на НАТО во Турција, а по критиките во Унгарија, рече дека самиот г...",
      "link": "https://makfax.com.mk/svet/evropa/video-ungarskiot-premier-na-dhet-ski-vo-turcija-%e2%80%9egodishen-odmor-s%c3%a8-sam-plativ%e2%80%9c/",
      "published": "Mon, 13 Jul 2026 07:47:07 +0000",
      "source_name": "МАКФАКС",
      "region": "🏔️ Балкан",
      "category": "Новости",
      "fetched_at": "2026-07-13 09:55:44",
      "language": "unknown"
    },
    {
      "title": "Астон Вила му го „грабна“ Манзамби на Њукалс",
      "summary": "Јохан Манзамби, се премисли, го одби Њукасл и ја прифати понудата од Астон Вила. Астон Вила буквално го грабна играчот од Њукасл во договор вреден реч...",
      "link": "https://makfax.com.mk/sport/aston-vila-mu-go-grabna-manzambi-na-njukals/",
      "published": "Mon, 13 Jul 2026 07:43:22 +0000",
      "source_name": "МАКФАКС",
      "region": "🏔️ Балкан",
      "category": "Новости",
      "fetched_at": "2026-07-13 09:55:44",
      "language": "unknown"
    },
    {
      "title": "(Фото) Тешка несреќа во Црна Гора: Загина 21-годишна девојка, дете тешко повредено",
      "summary": "Во тешка сообраќајна несреќа во Црна Гора загина 21-годишна девојка, а 16 други се повредени, објавува Vijesti.me. Несреќата се случила во градот Липц...",
      "link": "https://makfax.com.mk/svet/region/foto-teshka-nesreka-vo-crna-gora-zagina-21-godishna-devojka-dete-teshko-povredeno/",
      "published": "Mon, 13 Jul 2026 07:40:06 +0000",
      "source_name": "МАКФАКС",
      "region": "🏔️ Балкан",
      "category": "Новости",
      "fetched_at": "2026-07-13 09:55:44",
      "language": "unknown"
    },
    {
      "title": "(Фото) Руски дрон се урна и експлодираше во Молдавија",
      "summary": "Руски дрон денес го премина молдавскиот воздушен простор и се урна и експлодираше во близина на селото Копанка на југоистокот од земјата, објавија мол...",
      "link": "https://makfax.com.mk/svet/evropa/foto-ruski-dron-se-urna-i-eksplodirashe-vo-moldavija/",
      "published": "Mon, 13 Jul 2026 07:30:55 +0000",
      "source_name": "МАКФАКС",
      "region": "🏔️ Балкан",
      "category": "Новости",
      "fetched_at": "2026-07-13 09:55:44",
      "language": "unknown"
    },
    {
      "title": "Речиси 4.500 мртви во Венецуела, повеќе од 19.500 луѓе останаа без покрив над главата",
      "summary": "Бројот на жртви од катастрофалните земјотреси што ја погодија Венецуела се искачи на речиси 4.500 во неделата, а владата објави дека повеќе од 19.500 ...",
      "link": "https://makfax.com.mk/svet/rechisi-4-500-mrtvi-vo-venecuela-poveke-od-19-500-luge-ostanaa-bez-pokriv-nad-glavata/",
      "published": "Mon, 13 Jul 2026 07:26:51 +0000",
      "source_name": "МАКФАКС",
      "region": "🏔️ Балкан",
      "category": "Новости",
      "fetched_at": "2026-07-13 09:55:44",
      "language": "unknown"
    },
    {
      "title": "На Русија ѝ снемува гориво: Наставниците, под закана од отпуштање, ги чуваат редиците на бензинските",
      "summary": "Додека недостигот на гориво се влоши поради украинските напади врз нафтената инфраструктура, руските регионални власти преземаат итни мерки. Во регион...",
      "link": "https://makfax.com.mk/svet/na-rusija-%d1%9d-snemuva-gorivo-nastavnicite-pod-zakana-od-otpushtanje-gi-chuvaat-redicite-na-pumpite/",
      "published": "Mon, 13 Jul 2026 07:21:30 +0000",
      "source_name": "МАКФАКС",
      "region": "🏔️ Балкан",
      "category": "Новости",
      "fetched_at": "2026-07-13 09:55:44",
      "language": "unknown"
    },
    {
      "title": "At least 27 killed, 22 critically injured in Bangkok bar fire",
      "summary": "Firefighters arrived at the scene in the Chatuchak district to find patrons running through flames to escape.",
      "link": "https://www.bbc.co.uk/news/articles/c24yev53q06o?at_medium=RSS&at_campaign=rss",
      "published": "Mon, 13 Jul 2026 06:07:17 GMT",
      "source_name": "BBC News",
      "region": "🌍 World",
      "category": "Новости",
      "fetched_at": "2026-07-13 09:55:44",
      "language": "unknown"
    },
    {
      "title": "US senator and close Trump ally Lindsey Graham dies after 'brief and sudden illness'",
      "summary": "A spokesman for the 71-year-old South Carolina senator says initial findings suggest Graham's cause of death was related to his heart.",
      "link": "https://www.bbc.co.uk/news/articles/cvgj25j6nmeo?at_medium=RSS&at_campaign=rss",
      "published": "Sun, 12 Jul 2026 22:08:07 GMT",
      "source_name": "BBC News",
      "region": "🌍 World",
      "category": "Новости",
      "fetched_at": "2026-07-13 09:55:44",
      "language": "unknown"
    },
    {
      "title": "British couple return to village at heart of deadly Spanish wildfire",
      "summary": "At least 13 people, including five believed to be Britons, were killed by Thursday's wildfire in Spain's Almeria province.",
      "link": "https://www.bbc.co.uk/news/articles/cx24e09x79no?at_medium=RSS&at_campaign=rss",
      "published": "Mon, 13 Jul 2026 00:29:21 GMT",
      "source_name": "BBC News",
      "region": "🌍 World",
      "category": "Новости",
      "fetched_at": "2026-07-13 09:55:44",
      "language": "unknown"
    },
    {
      "title": "Planes sent to tackle wildfires of 'exceptional scale' near Paris",
      "summary": "It was the first time firefighting planes had been sent up from the normally drier and hotter south of the country to tackle fires in the Paris region...",
      "link": "https://www.bbc.co.uk/news/articles/clye4z168edo?at_medium=RSS&at_campaign=rss",
      "published": "Mon, 13 Jul 2026 03:36:09 GMT",
      "source_name": "BBC News",
      "region": "🌍 World",
      "category": "Новости",
      "fetched_at": "2026-07-13 09:55:44",
      "language": "unknown"
    },
    {
      "title": "US Senator Mitch McConnell says absence due to fall and pneumonia",
      "summary": "The veteran Republican says he will not return to work \"quite yet\", in his first statement following weeks of speculation about his health.",
      "link": "https://www.bbc.co.uk/news/articles/cvge2nd611zo?at_medium=RSS&at_campaign=rss",
      "published": "Sun, 12 Jul 2026 23:41:00 GMT",
      "source_name": "BBC News",
      "region": "🌍 World",
      "category": "Новости",
      "fetched_at": "2026-07-13 09:55:44",
      "language": "unknown"
    },
    {
      "title": "Anthony Zurcher: From Trump critic to ally, Lindsey Graham was a political survivor of the Maga era",
      "summary": "The senator's career was marked by a willingness to adapt to America's dramatically changing political climate, writes the BBC's North America corresp...",
      "link": "https://www.bbc.co.uk/news/articles/clyrdn216k2o?at_medium=RSS&at_campaign=rss",
      "published": "Sun, 12 Jul 2026 19:42:26 GMT",
      "source_name": "BBC News",
      "region": "🌍 World",
      "category": "Новости",
      "fetched_at": "2026-07-13 09:55:44",
      "language": "unknown"
    },
    {
      "title": "China evacuates nearly two million people as powerful typhoon makes landfall",
      "summary": "Schools, work and outdoor activities have been suspended in Zhejiang province and many transport services cancelled.",
      "link": "https://www.bbc.co.uk/news/articles/cdxd3wkp2rzo?at_medium=RSS&at_campaign=rss",
      "published": "Sun, 12 Jul 2026 07:39:45 GMT",
      "source_name": "BBC News",
      "region": "🌍 World",
      "category": "Новости",
      "fetched_at": "2026-07-13 09:55:44",
      "language": "unknown"
    },
    {
      "title": "T. rex could become most expensive fossil ever - but it's a ​problem for scientists",
      "summary": "A 67 million-year-old Tyrannosaurus rex will go on sale in New York with a pre-sale value of $30m.",
      "link": "https://www.bbc.co.uk/news/articles/c4gykgyn1r4o?at_medium=RSS&at_campaign=rss",
      "published": "Sat, 11 Jul 2026 23:58:40 GMT",
      "source_name": "BBC News",
      "region": "🌍 World",
      "category": "Новости",
      "fetched_at": "2026-07-13 09:55:44",
      "language": "unknown"
    },
    {
      "title": "Former Emir of Qatar Sheikh Hamad bin Khalifa Al Thani dies aged 74",
      "summary": "He took power in 1996 after staging a bloodless coup against his father, and went on to transform Qatar into the gas-rich power it is today.",
      "link": "https://www.bbc.co.uk/news/articles/cql1qdq14xro?at_medium=RSS&at_campaign=rss",
      "published": "Sun, 12 Jul 2026 16:35:50 GMT",
      "source_name": "BBC News",
      "region": "🌍 World",
      "category": "Новости",
      "fetched_at": "2026-07-13 09:55:44",
      "language": "unknown"
    },
    {
      "title": "David Willey, esteemed BBC Vatican correspondent, dies aged 93",
      "summary": "One of the BBC's longest-serving foreign correspondents, he reported on five popes during his career.",
      "link": "https://www.bbc.co.uk/news/articles/cn9403518jro?at_medium=RSS&at_campaign=rss",
      "published": "Sun, 12 Jul 2026 15:22:52 GMT",
      "source_name": "BBC News",
      "region": "🌍 World",
      "category": "Новости",
      "fetched_at": "2026-07-13 09:55:44",
      "language": "unknown"
    }
  ]
}