{
  "last_updated": "2026-04-28 19:14:32",
  "article_count": 20,
  "articles": [
    {
      "title": "ОАЕ го напуштаат ОПЕК",
      "summary": "Обединетите Арапски Емирати во вторник објавија дека ги напуштаат ОПЕК и ОПЕК+, што претставува голем удар за групата извозничка на нафта и нејзиниот ...",
      "link": "https://makfax.com.mk/svet/oae-go-napushtaat-opek/",
      "published": "Tue, 28 Apr 2026 17:13:43 +0000",
      "source_name": "МАКФАКС",
      "region": "🏔️ Балкан",
      "category": "Новости",
      "fetched_at": "2026-04-28 19:14:32",
      "language": "unknown"
    },
    {
      "title": "Тони Блер: Планот на Трамп за Газа ја запре војната",
      "summary": "Поранешниот британски премиер Тони Блер изјави дека израелската војна во Појасот Газа е запрена според планот на американскиот претседател Доналд Трам...",
      "link": "https://makfax.com.mk/svet/toni-bler-planot-na-tramp-za-gaza-ja-zapre-vojnata/",
      "published": "Tue, 28 Apr 2026 17:02:09 +0000",
      "source_name": "МАКФАКС",
      "region": "🏔️ Балкан",
      "category": "Новости",
      "fetched_at": "2026-04-28 19:14:32",
      "language": "unknown"
    },
    {
      "title": "Недостатокот на гориво се заканува да ги затвори помалите европски аеродроми",
      "summary": "Помалите европски аеродроми би можеле да се соочат со затворање доколку недостигот на гориво за авиони предизвикан од кризата на Блискиот Исток доведе...",
      "link": "https://makfax.com.mk/svet/evropa/nedostatokot-na-gorivo-se-zakanuva-da-gi-zatvori-pomalite-evropski-aerodromi/",
      "published": "Tue, 28 Apr 2026 16:47:55 +0000",
      "source_name": "МАКФАКС",
      "region": "🏔️ Балкан",
      "category": "Новости",
      "fetched_at": "2026-04-28 19:14:32",
      "language": "unknown"
    },
    {
      "title": "Портпарол на иранската војска: Војната не е завршена за нас",
      "summary": "Портпарол на иранската војска изјави за државната телевизија дека војната, и покрај прекинот на огнот, не е завршена за Иран. Изјавата дојде кратко вр...",
      "link": "https://makfax.com.mk/svet/portparol-na-iranskata-vojska-vojnata-ne-e-zavrshena-za-nas/",
      "published": "Tue, 28 Apr 2026 16:32:10 +0000",
      "source_name": "МАКФАКС",
      "region": "🏔️ Балкан",
      "category": "Новости",
      "fetched_at": "2026-04-28 19:14:32",
      "language": "unknown"
    },
    {
      "title": "(Фото/Видео) Трамп: На мајка ми ѝ се допаѓаше Чарлс, ѝ беше сладок",
      "summary": "Доналд Трамп одржа говор по повод државната посета на британското кралско семејство, истакнувајќи ја „вековната врска“ меѓу САД и Велика Британија. За...",
      "link": "https://makfax.com.mk/svet/foto-video-tramp-na-majka-mi-%d1%9d-se-dopagashe-charls-%d1%9d-beshe-sladok/",
      "published": "Tue, 28 Apr 2026 16:21:39 +0000",
      "source_name": "МАКФАКС",
      "region": "🏔️ Балкан",
      "category": "Новости",
      "fetched_at": "2026-04-28 19:14:32",
      "language": "unknown"
    },
    {
      "title": "Украинскиот парламент ја продолжи воената состојба и мобилизацијата за 90 дена",
      "summary": "Украинскиот парламент, Врховната рада, гласаше за продолжување на воената состојба и општата мобилизација за дополнителни 90 дена. Пратеникот Јарослав...",
      "link": "https://makfax.com.mk/svet/ukrainskiot-parlament-ja-prodolzhi-voenata-sostojba-i-mobilizacijata-za-90-dena/",
      "published": "Tue, 28 Apr 2026 16:14:23 +0000",
      "source_name": "МАКФАКС",
      "region": "🏔️ Балкан",
      "category": "Новости",
      "fetched_at": "2026-04-28 19:14:32",
      "language": "unknown"
    },
    {
      "title": "ССНМ и ЗНМ со крводарителска акција за 3 мај, Светскиот ден на слободата на медиумите",
      "summary": "По повод одбележување на Светскиот ден на слободата на медиумите, 3 мај, Самостојниот синдикат на новинари и медиумски работници и Здружението на нови...",
      "link": "https://makfax.com.mk/makedonija/ssnm-i-znm-so-krvodaritelska-akcija-za-3-maj-svetskiot-den-na-slobodata-na-mediumite/",
      "published": "Tue, 28 Apr 2026 16:09:28 +0000",
      "source_name": "МАКФАКС",
      "region": "🏔️ Балкан",
      "category": "Новости",
      "fetched_at": "2026-04-28 19:14:32",
      "language": "unknown"
    },
    {
      "title": "Франција: Иран никогаш не смее да добие нуклеарно оружје, но решението е дипломатија",
      "summary": "Франција изјави дека целта за спречување на Иран да развива нуклеарно оружје ќе се постигне преку дипломатски канали, изјави портпарол на Министерство...",
      "link": "https://makfax.com.mk/svet/francija-iran-nikogash-ne-smee-da-dobie-nuklearno-oruzhje-no-reshenieto-e-diplomatija/",
      "published": "Tue, 28 Apr 2026 16:07:41 +0000",
      "source_name": "МАКФАКС",
      "region": "🏔️ Балкан",
      "category": "Новости",
      "fetched_at": "2026-04-28 19:14:32",
      "language": "unknown"
    },
    {
      "title": "Трамп: Иран нè информираше дека е во состојба на колапс",
      "summary": "Американскиот претседател Доналд Трамп објави на својот профил на социјалните мрежи Truth Social дека Иран го информирал дека земјата е во состојба на...",
      "link": "https://makfax.com.mk/svet/tramp-iran-ne-informirashe-deka-e-vo-sostojba-na-kolaps/",
      "published": "Tue, 28 Apr 2026 15:41:07 +0000",
      "source_name": "МАКФАКС",
      "region": "🏔️ Балкан",
      "category": "Новости",
      "fetched_at": "2026-04-28 19:14:32",
      "language": "unknown"
    },
    {
      "title": "Дел од Центар утре без вода",
      "summary": "РЦУК Скопје известува дека утре дека поради уличен дефект ф-80 мм на булеварот Партизански Одреди 18б, прекинато водоснабдување ќе имаат корисниците о...",
      "link": "https://makfax.com.mk/makedonija/del-od-centar-utre-bez-voda/",
      "published": "Tue, 28 Apr 2026 15:18:24 +0000",
      "source_name": "МАКФАКС",
      "region": "🏔️ Балкан",
      "category": "Новости",
      "fetched_at": "2026-04-28 19:14:32",
      "language": "unknown"
    },
    {
      "title": "Suspect charged with attempted assassination of Trump at Washington dinner",
      "summary": "Investigators say the 31-year-old California man wanted to kill as many high-level officials as possible.",
      "link": "https://www.bbc.com/news/articles/cew7wez72vxo?at_medium=RSS&at_campaign=rss",
      "published": "Tue, 28 Apr 2026 00:41:48 GMT",
      "source_name": "BBC News",
      "region": "🌍 World",
      "category": "Новости",
      "fetched_at": "2026-04-28 19:14:32",
      "language": "unknown"
    },
    {
      "title": "US political violence generates a familiar cycle - this time it's in overdrive",
      "summary": "In modern America, it seems violence of this kind has become an ever-present storm that can strike anywhere and at any moment.",
      "link": "https://www.bbc.com/news/articles/cje4eeyq27lo?at_medium=RSS&at_campaign=rss",
      "published": "Tue, 28 Apr 2026 00:19:49 GMT",
      "source_name": "BBC News",
      "region": "🌍 World",
      "category": "Новости",
      "fetched_at": "2026-04-28 19:14:32",
      "language": "unknown"
    },
    {
      "title": "Jimmy Kimmel rejects White House criticism over Melania widow joke",
      "summary": "In a parody aired days before the White House Correspondents' Dinner, Kimmel called Melania an \"expectant widow\".",
      "link": "https://www.bbc.com/news/articles/c04x40d4424o?at_medium=RSS&at_campaign=rss",
      "published": "Tue, 28 Apr 2026 15:08:13 GMT",
      "source_name": "BBC News",
      "region": "🌍 World",
      "category": "Новости",
      "fetched_at": "2026-04-28 19:14:32",
      "language": "unknown"
    },
    {
      "title": "Russian superyacht sails through Strait of Hormuz despite blockade",
      "summary": "The 141m-long vessel, linked to a close ally of Russian President Vladimir Putin, cleared the waterway despite an ongoing blockade.",
      "link": "https://www.bbc.com/news/articles/cm2pn8zdxdjo?at_medium=RSS&at_campaign=rss",
      "published": "Tue, 28 Apr 2026 12:03:39 GMT",
      "source_name": "BBC News",
      "region": "🌍 World",
      "category": "Новости",
      "fetched_at": "2026-04-28 19:14:32",
      "language": "unknown"
    },
    {
      "title": "United Arab Emirates to quit oil cartel Opec",
      "summary": "The UAE's decision, after nearly 60 years of membership, is seen as a potential death knell for the oil cartel.",
      "link": "https://www.bbc.com/news/articles/cj4pxwlr52yo?at_medium=RSS&at_campaign=rss",
      "published": "Tue, 28 Apr 2026 16:24:45 GMT",
      "source_name": "BBC News",
      "region": "🌍 World",
      "category": "Новости",
      "fetched_at": "2026-04-28 19:14:32",
      "language": "unknown"
    },
    {
      "title": "Third Ukrainian strike hits Russian oil refinery and prompts evacuations",
      "summary": "Residents near a burning refinery in Tuapse are told to leave, and the Kremlin accuses Kyiv of destabilising global energy markets.",
      "link": "https://www.bbc.com/news/articles/cvgzd4qk7qgo?at_medium=RSS&at_campaign=rss",
      "published": "Tue, 28 Apr 2026 14:32:20 GMT",
      "source_name": "BBC News",
      "region": "🌍 World",
      "category": "Новости",
      "fetched_at": "2026-04-28 19:14:32",
      "language": "unknown"
    },
    {
      "title": "Suspected gunman aged 89 held in Greece after five wounded",
      "summary": "Five people were left with non-life-threatening injuries, according to Greece's state broadcaster ERT.",
      "link": "https://www.bbc.com/news/articles/cyv2pmz2v86o?at_medium=RSS&at_campaign=rss",
      "published": "Tue, 28 Apr 2026 14:59:30 GMT",
      "source_name": "BBC News",
      "region": "🌍 World",
      "category": "Новости",
      "fetched_at": "2026-04-28 19:14:32",
      "language": "unknown"
    },
    {
      "title": "Man admits plotting attack on Taylor Swift concert in Vienna",
      "summary": "The state prosecutor told the court that police found an almost completed bomb in a search of the man's house.",
      "link": "https://www.bbc.com/news/articles/c05d5qgprjzo?at_medium=RSS&at_campaign=rss",
      "published": "Tue, 28 Apr 2026 10:08:01 GMT",
      "source_name": "BBC News",
      "region": "🌍 World",
      "category": "Новости",
      "fetched_at": "2026-04-28 19:14:32",
      "language": "unknown"
    },
    {
      "title": "Rescuers race to free survivors trapped inside train after fatal Indonesia crash",
      "summary": "Two trains collided on the outskirts of the Indonesian capital on Monday, killing at least 15 people.",
      "link": "https://www.bbc.com/news/articles/ckgegg8r0v1o?at_medium=RSS&at_campaign=rss",
      "published": "Tue, 28 Apr 2026 04:18:54 GMT",
      "source_name": "BBC News",
      "region": "🌍 World",
      "category": "Новости",
      "fetched_at": "2026-04-28 19:14:32",
      "language": "unknown"
    },
    {
      "title": "Ukraine accuses Israel of receiving shipments of grain 'stolen' by Russia",
      "summary": "Israel's foreign minister says it has received no evidence to support the claim that a vessel carrying grain from occupied Ukraine has reached Haifa.",
      "link": "https://www.bbc.com/news/articles/cqjplqgd1r2o?at_medium=RSS&at_campaign=rss",
      "published": "Tue, 28 Apr 2026 13:51:51 GMT",
      "source_name": "BBC News",
      "region": "🌍 World",
      "category": "Новости",
      "fetched_at": "2026-04-28 19:14:32",
      "language": "unknown"
    }
  ]
}